ipfs_stac/__init__.py
ipfs_stac/client.py
ipfs_stac-0.2.0.dist-info/LICENSE
ipfs_stac-0.2.0.dist-info/METADATA
ipfs_stac-0.2.0.dist-info/WHEEL
ipfs_stac-0.2.0.dist-info/top_level.txt
ipfs_stac-0.2.0.dist-info/RECORD
