Metadata-Version: 2.1
Name: ipfs_stac
Version: 0.2.0
Summary: The EASIER Data Initiative Python IPFS-STAC Client
Author: The EASIER Data Initiative
License: MIT
Project-URL: Twitter, https://twitter.com/easierdataorg
Project-URL: GitHub, https://github.com/easierdata/ipfs-stac
License-File: LICENSE
Requires-Dist: ipfsspec
Requires-Dist: fsspec
Requires-Dist: requests
Requires-Dist: pandas
Requires-Dist: beautifulsoup4
Requires-Dist: pystac-client
Requires-Dist: Pillow
Requires-Dist: numpy
Requires-Dist: rasterio
Requires-Dist: yaspin
Requires-Dist: psutil
